AUTHORS.md
LICENSE
MANIFEST.in
README.md
setup.py
frankenz/__init__.py
frankenz/bruteforce.py
frankenz/fitting.py
frankenz/knn.py
frankenz/networks.py
frankenz/pdf.py
frankenz/plotting.py
frankenz/priors.py
frankenz/reddening.py
frankenz/simulate.py
frankenz.egg-info/PKG-INFO
frankenz.egg-info/SOURCES.txt
frankenz.egg-info/dependency_links.txt
frankenz.egg-info/requires.txt
frankenz.egg-info/top_level.txt
frankenz/filters/COSMOS.list
frankenz/filters/COSMOS.list~
frankenz/filters/Euclid.list
frankenz/filters/Euclid.list~
frankenz/filters/HSC.list
frankenz/filters/HSC.list~
frankenz/filters/LSST.list
frankenz/filters/LSST.list~
frankenz/filters/README.txt
frankenz/filters/README.txt~
frankenz/filters/SDSS.list
frankenz/filters/SDSS.list~
frankenz/filters/2mass/H_2mass.res
frankenz/filters/2mass/J_2mass.res
frankenz/filters/2mass/Ks_2mass.res
frankenz/filters/DECam/g_DEcam.res
frankenz/filters/DECam/i_DEcam.res
frankenz/filters/DECam/r_DEcam.res
frankenz/filters/DECam/u_DEcam.res
frankenz/filters/DECam/y_DEcam.res
frankenz/filters/DECam/z_DEcam.res
frankenz/filters/cfht/g_megaprime_sagem.res
frankenz/filters/cfht/i_megaprime_sagem.res
frankenz/filters/cfht/r_megaprime_sagem.res
frankenz/filters/cfht/u_megaprime_sagem.res
frankenz/filters/cfht/wircam_H.res
frankenz/filters/cfht/wircam_Ks.res
frankenz/filters/cfht/z_megaprime_sagem.res
frankenz/filters/ctio/flamingos_Ks.res
frankenz/filters/euclid/euclid_h.dat
frankenz/filters/euclid/euclid_j.dat
frankenz/filters/euclid/euclid_vis.dat
frankenz/filters/euclid/euclid_y.dat
frankenz/filters/galex/galex1500.res
frankenz/filters/galex/galex2500.res
frankenz/filters/herschel/PACS_filter_100.txt
frankenz/filters/herschel/PACS_filter_160.txt
frankenz/filters/herschel/SPIRE_filter_250.txt
frankenz/filters/herschel/SPIRE_filter_350.txt
frankenz/filters/herschel/SPIRE_filter_500.txt
frankenz/filters/hsc/hsc_g.dat
frankenz/filters/hsc/hsc_i.dat
frankenz/filters/hsc/hsc_r.dat
frankenz/filters/hsc/hsc_y.dat
frankenz/filters/hsc/hsc_z.dat
frankenz/filters/hst/ACS_F475W.res
frankenz/filters/hst/ACS_F606W.res
frankenz/filters/hst/ACS_F814W.res
frankenz/filters/hst/F300W_WFPC2.res
