Metadata-Version: 1.1
Name: frankenz
Version: 0.1.5
Summary: A photometric redshift monstrosity
Home-page: https://github.com/joshspeagle/frankenz
Author: Joshua S Speagle
Author-email: jspeagle@cfa.harvard.edu
License: MIT
Keywords: photo-z,photometric redshift,bayesian,template fitting,machine learning,nearest neighbors,self-organizing map,growing neural gas
Platform: UNKNOWN
Classifier: Development Status :: 3 - Alpha
Classifier: License :: OSI Approved :: MIT License
Classifier: Natural Language :: English
Classifier: Programming Language :: Python :: 2.7
Classifier: Programming Language :: Python :: 3.6
Classifier: Operating System :: OS Independent
Classifier: Topic :: Scientific/Engineering :: Astronomy
Classifier: Intended Audience :: Science/Research
